<?xml version="1.0" encoding="utf-8" standalone="yes"?>
<Spawners>
	<Spawner>
		<Name>TailorGuildmaster</Name>
		<Count>1</Count>
		<Location X="1388" Y="1599" Z="30" />
		<Map>Felucca</Map>
		<MinDelay>PT5M</MinDelay>
		<MaxDelay>PT10M</MaxDelay>
		<SpawnRange>0</SpawnRange>
		<HomeRange>5</HomeRange>
		<Flags>
			<ScaledDelay />
		</Flags>
	</Spawner>
	<Spawner>
		<Name>Armorer</Name>
		<Count>1</Count>
		<Location X="1362" Y="1574" Z="30" />
		<Map>Felucca</Map>
		<MinDelay>PT5M</MinDelay>
		<MaxDelay>PT10M</MaxDelay>
		<SpawnRange>0</SpawnRange>
		<HomeRange>5</HomeRange>
		<Flags>
			<ScaledDelay />
		</Flags>
	</Spawner>
	<Spawner>
		<Name>Weaver</Name>
		<Count>1</Count>
		<Location X="1388" Y="1599" Z="30" />
		<Map>Felucca</Map>
		<MinDelay>PT5M</MinDelay>
		<MaxDelay>PT10M</MaxDelay>
		<SpawnRange>0</SpawnRange>
		<HomeRange>5</HomeRange>
		<Flags>
			<ScaledDelay />
		</Flags>
	</Spawner>
	<Spawner>
		<Name>Regina</Name>
		<Count>1</Count>
		<Location X="1368" Y="1616" Z="50" />
		<Map>Felucca</Map>
		<MinDelay>PT5M</MinDelay>
		<MaxDelay>PT10M</MaxDelay>
		<SpawnRange>4</SpawnRange>
		<HomeRange>4</HomeRange>
		<Flags>
			<ScaledDelay />
		</Flags>
	</Spawner>
	<Spawner>
		<Name>Sheep</Name>
		<Count>7</Count>
		<Location X="1315" Y="1655" Z="31" />
		<Map>Felucca</Map>
		<MinDelay>PT10M</MinDelay>
		<MaxDelay>PT10M</MaxDelay>
		<SpawnRange>8</SpawnRange>
		<HomeRange>8</HomeRange>
		<Flags>
			<ScaledDelay />
		</Flags>
	</Spawner>
	<Spawner>
		<Name>OrderGuard</Name>
		<Count>1</Count>
		<Location X="1400" Y="1623" Z="28" />
		<Map>Felucca</Map>
		<MinDelay>PT5M</MinDelay>
		<MaxDelay>PT10M</MaxDelay>
		<SpawnRange>0</SpawnRange>
		<HomeRange>1</HomeRange>
		<Flags>
			<ScaledDelay />
		</Flags>
	</Spawner>
	<Spawner>
		<Name>OrderGuard</Name>
		<Count>1</Count>
		<Location X="1400" Y="1628" Z="28" />
		<Map>Felucca</Map>
		<MinDelay>PT5M</MinDelay>
		<MaxDelay>PT10M</MaxDelay>
		<SpawnRange>0</SpawnRange>
		<HomeRange>1</HomeRange>
		<Flags>
			<ScaledDelay />
		</Flags>
	</Spawner>
	<Spawner>
		<Name>AnimalTrainer</Name>
		<Count>1</Count>
		<Location X="1388" Y="1655" Z="30" />
		<Map>Felucca</Map>
		<MinDelay>PT5M</MinDelay>
		<MaxDelay>PT10M</MaxDelay>
		<SpawnRange>0</SpawnRange>
		<HomeRange>5</HomeRange>
		<Flags>
			<ScaledDelay />
		</Flags>
	</Spawner>
	<Spawner>
		<Name>Cow</Name>
		<Count>2</Count>
		<Location X="1315" Y="1655" Z="30" />
		<Map>Felucca</Map>
		<MinDelay>PT3M</MinDelay>
		<MaxDelay>PT10M</MaxDelay>
		<SpawnRange>6</SpawnRange>
		<HomeRange>6</HomeRange>
		<Flags>
			<Group />
			<ScaledDelay />
		</Flags>
	</Spawner>
	<Spawner>
		<Name>Veterinarian</Name>
		<Count>1</Count>
		<Location X="1388" Y="1654" Z="30" />
		<Map>Felucca</Map>
		<MinDelay>PT5M</MinDelay>
		<MaxDelay>PT10M</MaxDelay>
		<SpawnRange>4</SpawnRange>
		<HomeRange>4</HomeRange>
		<Flags>
			<ScaledDelay />
			<Saturable />
		</Flags>
	</Spawner>
	<Spawner>
		<Name>Tailor</Name>
		<Count>1</Count>
		<Location X="1388" Y="1599" Z="30" />
		<Map>Felucca</Map>
		<MinDelay>PT5M</MinDelay>
		<MaxDelay>PT10M</MaxDelay>
		<SpawnRange>0</SpawnRange>
		<HomeRange>5</HomeRange>
		<Flags>
			<ScaledDelay />
		</Flags>
	</Spawner>
	<Spawner>
		<Name>Weaponsmith</Name>
		<Count>1</Count>
		<Location X="1362" Y="1574" Z="30" />
		<Map>Felucca</Map>
		<MinDelay>PT5M</MinDelay>
		<MaxDelay>PT10M</MaxDelay>
		<SpawnRange>0</SpawnRange>
		<HomeRange>5</HomeRange>
		<Flags>
			<ScaledDelay />
		</Flags>
	</Spawner>
</Spawners>